[
  {
    "id": "ORD-1776627435151",
    "customer": {
      "name": "efrewf",
      "phone": "fewfewf",
      "address": "fewfwe"
    },
    "items": [
      {
        "id": "1",
        "name": "HP LaserJet M209d",
        "price": 289,
        "quantity": 1
      }
    ],
    "total": 289,
    "date": "2026-04-19T19:37:15.151Z",
    "status": "completed"
  },
  {
    "id": "ORD-1776628237969",
    "customer": {
      "name": "PLamen",
      "phone": "0890",
      "address": "RUSE CUBRFICA"
    },
    "items": [
      {
        "id": "1",
        "name": "HP LaserJet M209d",
        "price": 289,
        "quantity": 1
      }
    ],
    "total": 289,
    "date": "2026-04-19T19:50:37.969Z",
    "status": "new"
  },
  {
    "id": "ORD-1776633554610",
    "customer": {
      "name": "dsad",
      "phone": "sadsad",
      "address": "sadsada"
    },
    "items": [
      {
        "id": "4",
        "name": " PRINT ",
        "price": 89,
        "quantity": 5
      }
    ],
    "total": 445,
    "date": "2026-04-19T21:19:14.610Z",
    "status": "new"
  },
  {
    "id": "ORD-1777065165113",
    "customer": {
      "name": "dsadas",
      "phone": "das23123",
      "address": "21dwasda"
    },
    "items": [
      {
        "id": "20",
        "name": "Isopropyl Cleaning Fluid",
        "price": 26,
        "quantity": 1
      }
    ],
    "total": 26,
    "date": "2026-04-24T21:12:45.113Z",
    "status": "new"
  },
  {
    "id": "ORD-1777065178743",
    "customer": {
      "name": "3213edc21",
      "phone": "ecqcedwcaq",
      "address": "dcasdc"
    },
    "items": [
      {
        "id": "14",
        "name": "Arizona Chip 1",
        "price": 39,
        "quantity": 2
      }
    ],
    "total": 78,
    "date": "2026-04-24T21:12:58.743Z",
    "status": "new"
  },
  {
    "id": "ORD-1777065194015",
    "customer": {
      "name": "2e1ec",
      "phone": "12e21ce",
      "address": "21c"
    },
    "items": [
      {
        "id": "15",
        "name": "Arizona Toner 1",
        "price": 68,
        "quantity": 1
      }
    ],
    "total": 68,
    "date": "2026-04-24T21:13:14.015Z",
    "status": "new"
  },
  {
    "id": "ORD-1777065950495",
    "customer": {
      "name": "Poruchka1",
      "phone": "131290312",
      "address": "1293921i9",
      "courier": "Econt"
    },
    "items": [
      {
        "id": "14",
        "name": "Arizona Chip 1",
        "price": 39,
        "quantity": 1
      }
    ],
    "total": 39,
    "date": "2026-04-24T21:25:50.495Z",
    "status": "new"
  },
  {
    "id": "ORD-1777066120567",
    "customer": {
      "name": "Poruchka2",
      "phone": "3213",
      "address": "42313",
      "courier": "Econt"
    },
    "items": [
      {
        "id": "14",
        "name": "Arizona Chip 1",
        "price": 39,
        "quantity": 1
      }
    ],
    "total": 39,
    "date": "2026-04-24T21:28:40.567Z",
    "status": "new"
  },
  {
    "id": "ORD-1777066221072",
    "customer": {
      "name": "Poruchka3",
      "phone": "32132",
      "address": "1321321",
      "courier": "Econt"
    },
    "items": [
      {
        "id": "15",
        "name": "Arizona Toner 1",
        "price": 68,
        "quantity": 1
      }
    ],
    "total": 68,
    "date": "2026-04-24T21:30:21.072Z",
    "status": "new"
  },
  {
    "id": "ORD-1777066581492",
    "customer": {
      "name": "poruchka4",
      "phone": "213123",
      "address": "3213",
      "courier": "Econt"
    },
    "items": [
      {
        "id": "14",
        "name": "Arizona Chip 1",
        "price": 39,
        "quantity": 1
      }
    ],
    "total": 39,
    "date": "2026-04-24T21:36:21.492Z",
    "status": "new"
  },
  {
    "id": "ORD-1777066821926",
    "customer": {
      "name": "Poruchka5",
      "phone": "123123",
      "address": "3213",
      "courier": "Speedy"
    },
    "items": [
      {
        "id": "16",
        "name": "Arizona Chip 2",
        "price": 42,
        "quantity": 1
      }
    ],
    "total": 42,
    "date": "2026-04-24T21:40:21.926Z",
    "status": "new"
  },
  {
    "id": "ORD-1777066928026",
    "customer": {
      "name": "dsadas",
      "phone": "dsad",
      "address": "sadsada",
      "courier": "Econt"
    },
    "items": [
      {
        "id": "14",
        "name": "Arizona Chip 1",
        "price": 39,
        "quantity": 1
      }
    ],
    "total": 39,
    "date": "2026-04-24T21:42:08.026Z",
    "status": "new"
  },
  {
    "id": "ORD-1777471579636",
    "customer": {
      "name": "dsadas",
      "phone": "dsada",
      "address": "dsad",
      "courier": "Econt"
    },
    "items": [
      {
        "id": "custom-1777471570475",
        "name": "GT/XT 2240 - 255-OD - C - 1L",
        "price": 50,
        "quantity": 1,
        "selections": {
          "printerModel": [
            "GT/XT 2240"
          ],
          "chipType": [
            "255-OD"
          ],
          "color": [
            "C"
          ],
          "volume": [
            "1L"
          ]
        }
      }
    ],
    "total": 50,
    "date": "2026-04-29T14:06:19.636Z",
    "status": "new"
  },
  {
    "id": "ORD-1777499081988",
    "customer": {
      "name": "dsada",
      "phone": "sdasd",
      "address": "dasda",
      "courier": "Econt"
    },
    "items": [
      {
        "id": "custom-1777471604744",
        "name": "GT/XT 2240 - 255-OD - C - 1L",
        "price": 50,
        "quantity": 1,
        "selections": {
          "printerModel": [
            "GT/XT 2240"
          ],
          "chipType": [
            "255-OD"
          ],
          "color": [
            "C"
          ],
          "volume": [
            "1L"
          ]
        }
      },
      {
        "id": "custom-1777499074036",
        "name": "ACUITY-SELECT-HS-36 - KI - M - 2L",
        "price": 50,
        "quantity": 1,
        "selections": {
          "printerModel": [
            "ACUITY-SELECT-HS-36"
          ],
          "chipType": [
            "KI"
          ],
          "color": [
            "M"
          ],
          "volume": [
            "2L"
          ]
        }
      }
    ],
    "total": 100,
    "date": "2026-04-29T21:44:41.988Z",
    "status": "new"
  },
  {
    "id": "ORD-1777549705808",
    "customer": {
      "name": "ewqe",
      "phone": "qweqw",
      "address": "ewqe",
      "courier": "Econt"
    },
    "items": [
      {
        "id": "38",
        "name": "F1",
        "price": 23,
        "quantity": 1
      }
    ],
    "total": 23,
    "date": "2026-04-30T11:48:25.808Z",
    "status": "new"
  },
  {
    "id": "ORD-1777550571165",
    "customer": {
      "name": "31231",
      "phone": "23123",
      "address": "421412",
      "courier": "Econt"
    },
    "items": [
      {
        "id": "36",
        "name": "Изопропил5",
        "price": 5,
        "quantity": 1
      }
    ],
    "total": 5,
    "date": "2026-04-30T12:02:51.165Z",
    "status": "completed"
  }
]